sponet/__init__.py
sponet/cntm/__init__.py
sponet/cntm/model.py
sponet/cntm/parameters.py
sponet/cnvm/__init__.py
sponet/cnvm/approximations/__init__.py
sponet/cnvm/approximations/chemical_langevin_equation.py
sponet/cnvm/approximations/pair_approximation.py
sponet/cnvm/approximations/reaction_rate_equation.py
sponet/cnvm/approximations/stochastic_approximation.py
sponet/cnvm/model.py
sponet/cnvm/parameters.py
sponet/collective_variables.py
sponet/multiprocessing.py
sponet/network_generator.py
sponet/parameters.py
sponet/plotting.py
sponet/sample_moments.py
sponet/sampling.py
sponet/states.py
sponet/steady_state.py
sponet/utils.py
sponet-2.8.0.dist-info/LICENSE
sponet-2.8.0.dist-info/METADATA
sponet-2.8.0.dist-info/WHEEL
sponet-2.8.0.dist-info/RECORD
