Metadata-Version: 2.3
Name: sponet
Version: 2.8.0
Summary: Spreading Processes on Networks
License: GPL-3.0-or-later
Keywords: voter model,threshold model,social dynamics,opinion dynamics,statistical physics,agent-based model,epidemiology,interacting particle system
Author: Marvin Lücke
Requires-Python: >=3.10,<3.14
Classifier: Intended Audience :: Science/Research
Classifier: Topic :: Scientific/Engineering :: Mathematics
Classifier: Topic :: Scientific/Engineering :: Physics
Requires-Dist: matplotlib (>=3.6.0)
Requires-Dist: networkx (>=2.8.4)
Requires-Dist: numba (>=0.56)
Requires-Dist: scipy (>=1.9.3)
